{
  "2026-1-6-10-terrain1": "ENTRAINEMENT|Bastien Fleuret|Féminin|Compétition",
  "2026-1-6-10-terrain2": "ENTRAINEMENT|Bastien Fleuret|Féminin|Compétition",
  "2026-1-6-11-terrain1": "ENTRAINEMENT|Bastien Fleuret|Féminin|Compétition",
  "2026-1-6-11-terrain2": "ENTRAINEMENT|Bastien Fleuret|Féminin|Compétition",
  "2026-1-13-10-terrain1": "ENTRAINEMENT|Bastien Fleuret|Féminin|Compétition",
  "2026-1-13-10-terrain2": "ENTRAINEMENT|Bastien Fleuret|Féminin|Compétition",
  "2026-1-13-11-terrain1": "ENTRAINEMENT|Bastien Fleuret|Féminin|Compétition",
  "2026-1-13-11-terrain2": "ENTRAINEMENT|Bastien Fleuret|Féminin|Compétition",
  "2026-1-20-10-terrain1": "ENTRAINEMENT|Bastien Fleuret|Féminin|Compétition",
  "2026-1-20-10-terrain2": "ENTRAINEMENT|Bastien Fleuret|Féminin|Compétition",
  "2026-1-20-11-terrain1": "ENTRAINEMENT|Bastien Fleuret|Féminin|Compétition",
  "2026-1-20-11-terrain2": "ENTRAINEMENT|Bastien Fleuret|Féminin|Compétition",
  "2026-1-27-10-terrain1": "ENTRAINEMENT|Bastien Fleuret|Féminin|Compétition",
  "2026-1-27-10-terrain2": "ENTRAINEMENT|Bastien Fleuret|Féminin|Compétition",
  "2026-1-27-11-terrain1": "ENTRAINEMENT|Bastien Fleuret|Féminin|Compétition",
  "2026-1-27-11-terrain2": "ENTRAINEMENT|Bastien Fleuret|Féminin|Compétition",
  "2026-2-3-10-terrain1": "ENTRAINEMENT|Bastien Fleuret|Féminin|Compétition",
  "2026-2-3-10-terrain2": "ENTRAINEMENT|Bastien Fleuret|Féminin|Compétition",
  "2026-2-3-11-terrain1": "ENTRAINEMENT|Bastien Fleuret|Féminin|Compétition",
  "2026-2-3-11-terrain2": "ENTRAINEMENT|Bastien Fleuret|Féminin|Compétition",
  "2026-2-10-10-terrain1": "ENTRAINEMENT|Bastien Fleuret|Féminin|Compétition",
  "2026-2-10-10-terrain2": "ENTRAINEMENT|Bastien Fleuret|Féminin|Compétition",
  "2026-2-10-11-terrain1": "ENTRAINEMENT|Bastien Fleuret|Féminin|Compétition",
  "2026-2-10-11-terrain2": "ENTRAINEMENT|Bastien Fleuret|Féminin|Compétition",
  "2026-2-17-10-terrain1": "ENTRAINEMENT|Bastien Fleuret|Féminin|Compétition",
  "2026-2-17-10-terrain2": "ENTRAINEMENT|Bastien Fleuret|Féminin|Compétition",
  "2026-2-17-11-terrain1": "ENTRAINEMENT|Bastien Fleuret|Féminin|Compétition",
  "2026-2-17-11-terrain2": "ENTRAINEMENT|Bastien Fleuret|Féminin|Compétition",
  "2026-2-24-10-terrain1": "ENTRAINEMENT|Bastien Fleuret|Féminin|Compétition",
  "2026-2-24-10-terrain2": "ENTRAINEMENT|Bastien Fleuret|Féminin|Compétition",
  "2026-2-24-11-terrain1": "ENTRAINEMENT|Bastien Fleuret|Féminin|Compétition",
  "2026-2-24-11-terrain2": "ENTRAINEMENT|Bastien Fleuret|Féminin|Compétition",
  "2026-3-3-10-terrain1": "ENTRAINEMENT|Bastien Fleuret|Féminin|Compétition",
  "2026-3-3-10-terrain2": "ENTRAINEMENT|Bastien Fleuret|Féminin|Compétition",
  "2026-3-3-11-terrain1": "ENTRAINEMENT|Bastien Fleuret|Féminin|Compétition",
  "2026-3-3-11-terrain2": "ENTRAINEMENT|Bastien Fleuret|Féminin|Compétition",
  "2026-3-10-10-terrain1": "ENTRAINEMENT|Bastien Fleuret|Féminin|Compétition",
  "2026-3-10-10-terrain2": "ENTRAINEMENT|Bastien Fleuret|Féminin|Compétition",
  "2026-3-10-11-terrain1": "ENTRAINEMENT|Bastien Fleuret|Féminin|Compétition",
  "2026-3-10-11-terrain2": "ENTRAINEMENT|Bastien Fleuret|Féminin|Compétition",
  "2026-3-17-10-terrain1": "ENTRAINEMENT|Bastien Fleuret|Féminin|Compétition",
  "2026-3-17-10-terrain2": "ENTRAINEMENT|Bastien Fleuret|Féminin|Compétition",
  "2026-3-17-11-terrain1": "ENTRAINEMENT|Bastien Fleuret|Féminin|Compétition",
  "2026-3-17-11-terrain2": "ENTRAINEMENT|Bastien Fleuret|Féminin|Compétition",
  "2026-3-24-10-terrain1": "ENTRAINEMENT|Bastien Fleuret|Féminin|Compétition",
  "2026-3-24-10-terrain2": "ENTRAINEMENT|Bastien Fleuret|Féminin|Compétition",
  "2026-3-24-11-terrain1": "ENTRAINEMENT|Bastien Fleuret|Féminin|Compétition",
  "2026-3-24-11-terrain2": "ENTRAINEMENT|Bastien Fleuret|Féminin|Compétition",
  "2026-3-31-10-terrain1": "ENTRAINEMENT|Bastien Fleuret|Féminin|Compétition",
  "2026-3-31-10-terrain2": "ENTRAINEMENT|Bastien Fleuret|Féminin|Compétition",
  "2026-3-31-11-terrain1": "ENTRAINEMENT|Bastien Fleuret|Féminin|Compétition",
  "2026-3-31-11-terrain2": "ENTRAINEMENT|Bastien Fleuret|Féminin|Compétition",
  "2026-4-7-10-terrain1": "ENTRAINEMENT|Bastien Fleuret|Féminin|Compétition",
  "2026-4-7-10-terrain2": "ENTRAINEMENT|Bastien Fleuret|Féminin|Compétition",
  "2026-4-7-11-terrain1": "ENTRAINEMENT|Bastien Fleuret|Féminin|Compétition",
  "2026-4-7-11-terrain2": "ENTRAINEMENT|Bastien Fleuret|Féminin|Compétition",
  "2026-4-14-10-terrain1": "ENTRAINEMENT|Bastien Fleuret|Féminin|Compétition",
  "2026-4-14-10-terrain2": "ENTRAINEMENT|Bastien Fleuret|Féminin|Compétition",
  "2026-4-14-11-terrain1": "ENTRAINEMENT|Bastien Fleuret|Féminin|Compétition",
  "2026-4-14-11-terrain2": "ENTRAINEMENT|Bastien Fleuret|Féminin|Compétition",
  "2026-4-21-10-terrain1": "ENTRAINEMENT|Bastien Fleuret|Féminin|Compétition",
  "2026-4-21-10-terrain2": "ENTRAINEMENT|Bastien Fleuret|Féminin|Compétition",
  "2026-4-21-11-terrain1": "ENTRAINEMENT|Bastien Fleuret|Féminin|Compétition",
  "2026-4-21-11-terrain2": "ENTRAINEMENT|Bastien Fleuret|Féminin|Compétition",
  "2026-4-28-10-terrain1": "ENTRAINEMENT|Bastien Fleuret|Féminin|Compétition",
  "2026-4-28-10-terrain2": "ENTRAINEMENT|Bastien Fleuret|Féminin|Compétition",
  "2026-4-28-11-terrain1": "ENTRAINEMENT|Bastien Fleuret|Féminin|Compétition",
  "2026-4-28-11-terrain2": "ENTRAINEMENT|Bastien Fleuret|Féminin|Compétition",
  "2026-5-5-10-terrain1": "ENTRAINEMENT|Bastien Fleuret|Féminin|Compétition",
  "2026-5-5-10-terrain2": "ENTRAINEMENT|Bastien Fleuret|Féminin|Compétition",
  "2026-5-5-11-terrain1": "ENTRAINEMENT|Bastien Fleuret|Féminin|Compétition",
  "2026-5-5-11-terrain2": "ENTRAINEMENT|Bastien Fleuret|Féminin|Compétition",
  "2026-5-12-10-terrain1": "ENTRAINEMENT|Bastien Fleuret|Féminin|Compétition",
  "2026-5-12-10-terrain2": "ENTRAINEMENT|Bastien Fleuret|Féminin|Compétition",
  "2026-5-12-11-terrain1": "ENTRAINEMENT|Bastien Fleuret|Féminin|Compétition",
  "2026-5-12-11-terrain2": "ENTRAINEMENT|Bastien Fleuret|Féminin|Compétition",
  "2026-5-19-10-terrain1": "ENTRAINEMENT|Bastien Fleuret|Féminin|Compétition",
  "2026-5-19-10-terrain2": "ENTRAINEMENT|Bastien Fleuret|Féminin|Compétition",
  "2026-5-19-11-terrain1": "ENTRAINEMENT|Bastien Fleuret|Féminin|Compétition",
  "2026-5-19-11-terrain2": "ENTRAINEMENT|Bastien Fleuret|Féminin|Compétition",
  "2026-5-26-10-terrain1": "ENTRAINEMENT|Bastien Fleuret|Féminin|Compétition",
  "2026-5-26-10-terrain2": "ENTRAINEMENT|Bastien Fleuret|Féminin|Compétition",
  "2026-5-26-11-terrain1": "ENTRAINEMENT|Bastien Fleuret|Féminin|Compétition",
  "2026-5-26-11-terrain2": "ENTRAINEMENT|Bastien Fleuret|Féminin|Compétition",
  "2026-6-2-10-terrain1": "ENTRAINEMENT|Bastien Fleuret|Féminin|Compétition",
  "2026-6-2-10-terrain2": "ENTRAINEMENT|Bastien Fleuret|Féminin|Compétition",
  "2026-6-2-11-terrain1": "ENTRAINEMENT|Bastien Fleuret|Féminin|Compétition",
  "2026-6-2-11-terrain2": "ENTRAINEMENT|Bastien Fleuret|Féminin|Compétition",
  "2026-6-9-10-terrain1": "ENTRAINEMENT|Bastien Fleuret|Féminin|Compétition",
  "2026-6-9-10-terrain2": "ENTRAINEMENT|Bastien Fleuret|Féminin|Compétition",
  "2026-6-9-11-terrain1": "ENTRAINEMENT|Bastien Fleuret|Féminin|Compétition",
  "2026-6-9-11-terrain2": "ENTRAINEMENT|Bastien Fleuret|Féminin|Compétition",
  "2026-6-16-10-terrain1": "ENTRAINEMENT|Bastien Fleuret|Féminin|Compétition",
  "2026-6-16-10-terrain2": "ENTRAINEMENT|Bastien Fleuret|Féminin|Compétition",
  "2026-6-16-11-terrain1": "ENTRAINEMENT|Bastien Fleuret|Féminin|Compétition",
  "2026-6-16-11-terrain2": "ENTRAINEMENT|Bastien Fleuret|Féminin|Compétition",
  "2026-6-23-10-terrain1": "ENTRAINEMENT|Bastien Fleuret|Féminin|Compétition",
  "2026-6-23-10-terrain2": "ENTRAINEMENT|Bastien Fleuret|Féminin|Compétition",
  "2026-6-23-11-terrain1": "ENTRAINEMENT|Bastien Fleuret|Féminin|Compétition",
  "2026-6-23-11-terrain2": "ENTRAINEMENT|Bastien Fleuret|Féminin|Compétition",
  "2026-6-30-10-terrain1": "ENTRAINEMENT|Bastien Fleuret|Féminin|Compétition",
  "2026-6-30-10-terrain2": "ENTRAINEMENT|Bastien Fleuret|Féminin|Compétition",
  "2026-6-30-11-terrain1": "ENTRAINEMENT|Bastien Fleuret|Féminin|Compétition",
  "2026-6-30-11-terrain2": "ENTRAINEMENT|Bastien Fleuret|Féminin|Compétition",
  "2026-7-7-10-terrain1": "ENTRAINEMENT|Bastien Fleuret|Féminin|Compétition",
  "2026-7-7-10-terrain2": "ENTRAINEMENT|Bastien Fleuret|Féminin|Compétition",
  "2026-7-7-11-terrain1": "ENTRAINEMENT|Bastien Fleuret|Féminin|Compétition",
  "2026-7-7-11-terrain2": "ENTRAINEMENT|Bastien Fleuret|Féminin|Compétition",
  "2026-7-14-10-terrain1": "ENTRAINEMENT|Bastien Fleuret|Féminin|Compétition",
  "2026-7-14-10-terrain2": "ENTRAINEMENT|Bastien Fleuret|Féminin|Compétition",
  "2026-7-14-11-terrain1": "ENTRAINEMENT|Bastien Fleuret|Féminin|Compétition",
  "2026-7-14-11-terrain2": "ENTRAINEMENT|Bastien Fleuret|Féminin|Compétition",
  "2026-7-21-10-terrain1": "ENTRAINEMENT|Bastien Fleuret|Féminin|Compétition",
  "2026-7-21-10-terrain2": "ENTRAINEMENT|Bastien Fleuret|Féminin|Compétition",
  "2026-7-21-11-terrain1": "ENTRAINEMENT|Bastien Fleuret|Féminin|Compétition",
  "2026-7-21-11-terrain2": "ENTRAINEMENT|Bastien Fleuret|Féminin|Compétition",
  "2026-7-28-10-terrain1": "ENTRAINEMENT|Bastien Fleuret|Féminin|Compétition",
  "2026-7-28-10-terrain2": "ENTRAINEMENT|Bastien Fleuret|Féminin|Compétition",
  "2026-7-28-11-terrain1": "ENTRAINEMENT|Bastien Fleuret|Féminin|Compétition",
  "2026-7-28-11-terrain2": "ENTRAINEMENT|Bastien Fleuret|Féminin|Compétition",
  "2026-8-4-10-terrain1": "ENTRAINEMENT|Bastien Fleuret|Féminin|Compétition",
  "2026-8-4-10-terrain2": "ENTRAINEMENT|Bastien Fleuret|Féminin|Compétition",
  "2026-8-4-11-terrain1": "ENTRAINEMENT|Bastien Fleuret|Féminin|Compétition",
  "2026-8-4-11-terrain2": "ENTRAINEMENT|Bastien Fleuret|Féminin|Compétition",
  "2026-8-11-10-terrain1": "ENTRAINEMENT|Bastien Fleuret|Féminin|Compétition",
  "2026-8-11-10-terrain2": "ENTRAINEMENT|Bastien Fleuret|Féminin|Compétition",
  "2026-8-11-11-terrain1": "ENTRAINEMENT|Bastien Fleuret|Féminin|Compétition",
  "2026-8-11-11-terrain2": "ENTRAINEMENT|Bastien Fleuret|Féminin|Compétition",
  "2026-8-18-10-terrain1": "ENTRAINEMENT|Bastien Fleuret|Féminin|Compétition",
  "2026-8-18-10-terrain2": "ENTRAINEMENT|Bastien Fleuret|Féminin|Compétition",
  "2026-8-18-11-terrain1": "ENTRAINEMENT|Bastien Fleuret|Féminin|Compétition",
  "2026-8-18-11-terrain2": "ENTRAINEMENT|Bastien Fleuret|Féminin|Compétition",
  "2026-8-25-10-terrain1": "ENTRAINEMENT|Bastien Fleuret|Féminin|Compétition",
  "2026-8-25-10-terrain2": "ENTRAINEMENT|Bastien Fleuret|Féminin|Compétition",
  "2026-8-25-11-terrain1": "ENTRAINEMENT|Bastien Fleuret|Féminin|Compétition",
  "2026-8-25-11-terrain2": "ENTRAINEMENT|Bastien Fleuret|Féminin|Compétition",
  "2026-9-1-10-terrain1": "ENTRAINEMENT|Bastien Fleuret|Féminin|Compétition",
  "2026-9-1-10-terrain2": "ENTRAINEMENT|Bastien Fleuret|Féminin|Compétition",
  "2026-9-1-11-terrain1": "ENTRAINEMENT|Bastien Fleuret|Féminin|Compétition",
  "2026-9-1-11-terrain2": "ENTRAINEMENT|Bastien Fleuret|Féminin|Compétition",
  "2026-9-8-10-terrain1": "ENTRAINEMENT|Bastien Fleuret|Féminin|Compétition",
  "2026-9-8-10-terrain2": "ENTRAINEMENT|Bastien Fleuret|Féminin|Compétition",
  "2026-9-8-11-terrain1": "ENTRAINEMENT|Bastien Fleuret|Féminin|Compétition",
  "2026-9-8-11-terrain2": "ENTRAINEMENT|Bastien Fleuret|Féminin|Compétition",
  "2026-9-15-10-terrain1": "ENTRAINEMENT|Bastien Fleuret|Féminin|Compétition",
  "2026-9-15-10-terrain2": "ENTRAINEMENT|Bastien Fleuret|Féminin|Compétition",
  "2026-9-15-11-terrain1": "ENTRAINEMENT|Bastien Fleuret|Féminin|Compétition",
  "2026-9-15-11-terrain2": "ENTRAINEMENT|Bastien Fleuret|Féminin|Compétition",
  "2026-9-22-10-terrain1": "ENTRAINEMENT|Bastien Fleuret|Féminin|Compétition",
  "2026-9-22-10-terrain2": "ENTRAINEMENT|Bastien Fleuret|Féminin|Compétition",
  "2026-9-22-11-terrain1": "ENTRAINEMENT|Bastien Fleuret|Féminin|Compétition",
  "2026-9-22-11-terrain2": "ENTRAINEMENT|Bastien Fleuret|Féminin|Compétition",
  "2026-9-29-10-terrain1": "ENTRAINEMENT|Bastien Fleuret|Féminin|Compétition",
  "2026-9-29-10-terrain2": "ENTRAINEMENT|Bastien Fleuret|Féminin|Compétition",
  "2026-9-29-11-terrain1": "ENTRAINEMENT|Bastien Fleuret|Féminin|Compétition",
  "2026-9-29-11-terrain2": "ENTRAINEMENT|Bastien Fleuret|Féminin|Compétition",
  "2026-10-6-10-terrain1": "ENTRAINEMENT|Bastien Fleuret|Féminin|Compétition",
  "2026-10-6-10-terrain2": "ENTRAINEMENT|Bastien Fleuret|Féminin|Compétition",
  "2026-10-6-11-terrain1": "ENTRAINEMENT|Bastien Fleuret|Féminin|Compétition",
  "2026-10-6-11-terrain2": "ENTRAINEMENT|Bastien Fleuret|Féminin|Compétition",
  "2026-10-13-10-terrain1": "ENTRAINEMENT|Bastien Fleuret|Féminin|Compétition",
  "2026-10-13-10-terrain2": "ENTRAINEMENT|Bastien Fleuret|Féminin|Compétition",
  "2026-10-13-11-terrain1": "ENTRAINEMENT|Bastien Fleuret|Féminin|Compétition",
  "2026-10-13-11-terrain2": "ENTRAINEMENT|Bastien Fleuret|Féminin|Compétition",
  "2026-10-20-10-terrain1": "ENTRAINEMENT|Bastien Fleuret|Féminin|Compétition",
  "2026-10-20-10-terrain2": "ENTRAINEMENT|Bastien Fleuret|Féminin|Compétition",
  "2026-10-20-11-terrain1": "ENTRAINEMENT|Bastien Fleuret|Féminin|Compétition",
  "2026-10-20-11-terrain2": "ENTRAINEMENT|Bastien Fleuret|Féminin|Compétition",
  "2026-10-27-10-terrain1": "ENTRAINEMENT|Bastien Fleuret|Féminin|Compétition",
  "2026-10-27-10-terrain2": "ENTRAINEMENT|Bastien Fleuret|Féminin|Compétition",
  "2026-10-27-11-terrain1": "ENTRAINEMENT|Bastien Fleuret|Féminin|Compétition",
  "2026-10-27-11-terrain2": "ENTRAINEMENT|Bastien Fleuret|Féminin|Compétition",
  "2026-11-3-10-terrain1": "ENTRAINEMENT|Bastien Fleuret|Féminin|Compétition",
  "2026-11-3-10-terrain2": "ENTRAINEMENT|Bastien Fleuret|Féminin|Compétition",
  "2026-11-3-11-terrain1": "ENTRAINEMENT|Bastien Fleuret|Féminin|Compétition",
  "2026-11-3-11-terrain2": "ENTRAINEMENT|Bastien Fleuret|Féminin|Compétition",
  "2026-11-10-10-terrain1": "ENTRAINEMENT|Bastien Fleuret|Féminin|Compétition",
  "2026-11-10-10-terrain2": "ENTRAINEMENT|Bastien Fleuret|Féminin|Compétition",
  "2026-11-10-11-terrain1": "ENTRAINEMENT|Bastien Fleuret|Féminin|Compétition",
  "2026-11-10-11-terrain2": "ENTRAINEMENT|Bastien Fleuret|Féminin|Compétition",
  "2026-11-17-10-terrain1": "ENTRAINEMENT|Bastien Fleuret|Féminin|Compétition",
  "2026-11-17-10-terrain2": "ENTRAINEMENT|Bastien Fleuret|Féminin|Compétition",
  "2026-11-17-11-terrain1": "ENTRAINEMENT|Bastien Fleuret|Féminin|Compétition",
  "2026-11-17-11-terrain2": "ENTRAINEMENT|Bastien Fleuret|Féminin|Compétition",
  "2026-11-24-10-terrain1": "ENTRAINEMENT|Bastien Fleuret|Féminin|Compétition",
  "2026-11-24-10-terrain2": "ENTRAINEMENT|Bastien Fleuret|Féminin|Compétition",
  "2026-11-24-11-terrain1": "ENTRAINEMENT|Bastien Fleuret|Féminin|Compétition",
  "2026-11-24-11-terrain2": "ENTRAINEMENT|Bastien Fleuret|Féminin|Compétition",
  "2026-12-1-10-terrain1": "ENTRAINEMENT|Bastien Fleuret|Féminin|Compétition",
  "2026-12-1-10-terrain2": "ENTRAINEMENT|Bastien Fleuret|Féminin|Compétition",
  "2026-12-1-11-terrain1": "ENTRAINEMENT|Bastien Fleuret|Féminin|Compétition",
  "2026-12-1-11-terrain2": "ENTRAINEMENT|Bastien Fleuret|Féminin|Compétition",
  "2026-12-8-10-terrain1": "ENTRAINEMENT|Bastien Fleuret|Féminin|Compétition",
  "2026-12-8-10-terrain2": "ENTRAINEMENT|Bastien Fleuret|Féminin|Compétition",
  "2026-12-8-11-terrain1": "ENTRAINEMENT|Bastien Fleuret|Féminin|Compétition",
  "2026-12-8-11-terrain2": "ENTRAINEMENT|Bastien Fleuret|Féminin|Compétition",
  "2026-12-15-10-terrain1": "ENTRAINEMENT|Bastien Fleuret|Féminin|Compétition",
  "2026-12-15-10-terrain2": "ENTRAINEMENT|Bastien Fleuret|Féminin|Compétition",
  "2026-12-15-11-terrain1": "ENTRAINEMENT|Bastien Fleuret|Féminin|Compétition",
  "2026-12-15-11-terrain2": "ENTRAINEMENT|Bastien Fleuret|Féminin|Compétition",
  "2026-12-22-10-terrain1": "ENTRAINEMENT|Bastien Fleuret|Féminin|Compétition",
  "2026-12-22-10-terrain2": "ENTRAINEMENT|Bastien Fleuret|Féminin|Compétition",
  "2026-12-22-11-terrain1": "ENTRAINEMENT|Bastien Fleuret|Féminin|Compétition",
  "2026-12-22-11-terrain2": "ENTRAINEMENT|Bastien Fleuret|Féminin|Compétition",
  "2026-12-29-10-terrain1": "ENTRAINEMENT|Bastien Fleuret|Féminin|Compétition",
  "2026-12-29-10-terrain2": "ENTRAINEMENT|Bastien Fleuret|Féminin|Compétition",
  "2026-12-29-11-terrain1": "ENTRAINEMENT|Bastien Fleuret|Féminin|Compétition",
  "2026-12-29-11-terrain2": "ENTRAINEMENT|Bastien Fleuret|Féminin|Compétition",
  "2026-1-5-10-terrain1": "ENTRAINEMENT|Marie Martin|Mixte|Débutant",
  "2026-1-5-11-terrain1": "ENTRAINEMENT|Marie Martin|Mixte|Débutant",
  "2026-1-12-10-terrain1": "ENTRAINEMENT|Marie Martin|Mixte|Débutant",
  "2026-1-12-11-terrain1": "ENTRAINEMENT|Marie Martin|Mixte|Débutant",
  "2026-1-19-10-terrain1": "ENTRAINEMENT|Marie Martin|Mixte|Débutant",
  "2026-1-19-11-terrain1": "ENTRAINEMENT|Marie Martin|Mixte|Débutant",
  "2026-1-26-10-terrain1": "ENTRAINEMENT|Marie Martin|Mixte|Débutant",
  "2026-1-26-11-terrain1": "ENTRAINEMENT|Marie Martin|Mixte|Débutant",
  "2026-2-2-10-terrain1": "ENTRAINEMENT|Marie Martin|Mixte|Débutant",
  "2026-2-2-11-terrain1": "ENTRAINEMENT|Marie Martin|Mixte|Débutant",
  "2026-2-9-10-terrain1": "ENTRAINEMENT|Marie Martin|Mixte|Débutant",
  "2026-2-9-11-terrain1": "ENTRAINEMENT|Marie Martin|Mixte|Débutant",
  "2026-2-16-10-terrain1": "ENTRAINEMENT|Marie Martin|Mixte|Débutant",
  "2026-2-16-11-terrain1": "ENTRAINEMENT|Marie Martin|Mixte|Débutant",
  "2026-2-23-10-terrain1": "ENTRAINEMENT|Marie Martin|Mixte|Débutant",
  "2026-2-23-11-terrain1": "ENTRAINEMENT|Marie Martin|Mixte|Débutant",
  "2026-3-2-10-terrain1": "ENTRAINEMENT|Marie Martin|Mixte|Débutant",
  "2026-3-2-11-terrain1": "ENTRAINEMENT|Marie Martin|Mixte|Débutant",
  "2026-3-9-10-terrain1": "ENTRAINEMENT|Marie Martin|Mixte|Débutant",
  "2026-3-9-11-terrain1": "ENTRAINEMENT|Marie Martin|Mixte|Débutant",
  "2026-3-16-10-terrain1": "ENTRAINEMENT|Marie Martin|Mixte|Débutant",
  "2026-3-16-11-terrain1": "ENTRAINEMENT|Marie Martin|Mixte|Débutant",
  "2026-3-23-10-terrain1": "ENTRAINEMENT|Marie Martin|Mixte|Débutant",
  "2026-3-23-11-terrain1": "ENTRAINEMENT|Marie Martin|Mixte|Débutant",
  "2026-3-30-10-terrain1": "ENTRAINEMENT|Marie Martin|Mixte|Débutant",
  "2026-3-30-11-terrain1": "ENTRAINEMENT|Marie Martin|Mixte|Débutant",
  "2026-4-6-10-terrain1": "ENTRAINEMENT|Marie Martin|Mixte|Débutant",
  "2026-4-6-11-terrain1": "ENTRAINEMENT|Marie Martin|Mixte|Débutant",
  "2026-4-13-10-terrain1": "ENTRAINEMENT|Marie Martin|Mixte|Débutant",
  "2026-4-13-11-terrain1": "ENTRAINEMENT|Marie Martin|Mixte|Débutant",
  "2026-4-20-10-terrain1": "ENTRAINEMENT|Marie Martin|Mixte|Débutant",
  "2026-4-20-11-terrain1": "ENTRAINEMENT|Marie Martin|Mixte|Débutant",
  "2026-4-27-10-terrain1": "ENTRAINEMENT|Marie Martin|Mixte|Débutant",
  "2026-4-27-11-terrain1": "ENTRAINEMENT|Marie Martin|Mixte|Débutant",
  "2026-5-4-10-terrain1": "ENTRAINEMENT|Marie Martin|Mixte|Débutant",
  "2026-5-4-11-terrain1": "ENTRAINEMENT|Marie Martin|Mixte|Débutant",
  "2026-5-11-10-terrain1": "ENTRAINEMENT|Marie Martin|Mixte|Débutant",
  "2026-5-11-11-terrain1": "ENTRAINEMENT|Marie Martin|Mixte|Débutant",
  "2026-5-18-10-terrain1": "ENTRAINEMENT|Marie Martin|Mixte|Débutant",
  "2026-5-18-11-terrain1": "ENTRAINEMENT|Marie Martin|Mixte|Débutant",
  "2026-5-25-10-terrain1": "ENTRAINEMENT|Marie Martin|Mixte|Débutant",
  "2026-5-25-11-terrain1": "ENTRAINEMENT|Marie Martin|Mixte|Débutant",
  "2026-6-1-10-terrain1": "ENTRAINEMENT|Marie Martin|Mixte|Débutant",
  "2026-6-1-11-terrain1": "ENTRAINEMENT|Marie Martin|Mixte|Débutant",
  "2026-6-8-10-terrain1": "ENTRAINEMENT|Marie Martin|Mixte|Débutant",
  "2026-6-8-11-terrain1": "ENTRAINEMENT|Marie Martin|Mixte|Débutant",
  "2026-6-15-10-terrain1": "ENTRAINEMENT|Marie Martin|Mixte|Débutant",
  "2026-6-15-11-terrain1": "ENTRAINEMENT|Marie Martin|Mixte|Débutant",
  "2026-6-22-10-terrain1": "ENTRAINEMENT|Marie Martin|Mixte|Débutant",
  "2026-6-22-11-terrain1": "ENTRAINEMENT|Marie Martin|Mixte|Débutant",
  "2026-6-29-10-terrain1": "ENTRAINEMENT|Marie Martin|Mixte|Débutant",
  "2026-6-29-11-terrain1": "ENTRAINEMENT|Marie Martin|Mixte|Débutant",
  "2026-7-6-10-terrain1": "ENTRAINEMENT|Marie Martin|Mixte|Débutant",
  "2026-7-6-11-terrain1": "ENTRAINEMENT|Marie Martin|Mixte|Débutant",
  "2026-7-13-10-terrain1": "ENTRAINEMENT|Marie Martin|Mixte|Débutant",
  "2026-7-13-11-terrain1": "ENTRAINEMENT|Marie Martin|Mixte|Débutant",
  "2026-7-20-10-terrain1": "ENTRAINEMENT|Marie Martin|Mixte|Débutant",
  "2026-7-20-11-terrain1": "ENTRAINEMENT|Marie Martin|Mixte|Débutant",
  "2026-7-27-10-terrain1": "ENTRAINEMENT|Marie Martin|Mixte|Débutant",
  "2026-7-27-11-terrain1": "ENTRAINEMENT|Marie Martin|Mixte|Débutant",
  "2026-8-3-10-terrain1": "ENTRAINEMENT|Marie Martin|Mixte|Débutant",
  "2026-8-3-11-terrain1": "ENTRAINEMENT|Marie Martin|Mixte|Débutant",
  "2026-8-10-10-terrain1": "ENTRAINEMENT|Marie Martin|Mixte|Débutant",
  "2026-8-10-11-terrain1": "ENTRAINEMENT|Marie Martin|Mixte|Débutant",
  "2026-8-17-10-terrain1": "ENTRAINEMENT|Marie Martin|Mixte|Débutant",
  "2026-8-17-11-terrain1": "ENTRAINEMENT|Marie Martin|Mixte|Débutant",
  "2026-8-24-10-terrain1": "ENTRAINEMENT|Marie Martin|Mixte|Débutant",
  "2026-8-24-11-terrain1": "ENTRAINEMENT|Marie Martin|Mixte|Débutant",
  "2026-8-31-10-terrain1": "ENTRAINEMENT|Marie Martin|Mixte|Débutant",
  "2026-8-31-11-terrain1": "ENTRAINEMENT|Marie Martin|Mixte|Débutant",
  "2026-9-7-10-terrain1": "ENTRAINEMENT|Marie Martin|Mixte|Débutant",
  "2026-9-7-11-terrain1": "ENTRAINEMENT|Marie Martin|Mixte|Débutant",
  "2026-9-14-10-terrain1": "ENTRAINEMENT|Marie Martin|Mixte|Débutant",
  "2026-9-14-11-terrain1": "ENTRAINEMENT|Marie Martin|Mixte|Débutant",
  "2026-9-21-10-terrain1": "ENTRAINEMENT|Marie Martin|Mixte|Débutant",
  "2026-9-21-11-terrain1": "ENTRAINEMENT|Marie Martin|Mixte|Débutant",
  "2026-9-28-10-terrain1": "ENTRAINEMENT|Marie Martin|Mixte|Débutant",
  "2026-9-28-11-terrain1": "ENTRAINEMENT|Marie Martin|Mixte|Débutant",
  "2026-10-5-10-terrain1": "ENTRAINEMENT|Marie Martin|Mixte|Débutant",
  "2026-10-5-11-terrain1": "ENTRAINEMENT|Marie Martin|Mixte|Débutant",
  "2026-10-12-10-terrain1": "ENTRAINEMENT|Marie Martin|Mixte|Débutant",
  "2026-10-12-11-terrain1": "ENTRAINEMENT|Marie Martin|Mixte|Débutant",
  "2026-10-19-10-terrain1": "ENTRAINEMENT|Marie Martin|Mixte|Débutant",
  "2026-10-19-11-terrain1": "ENTRAINEMENT|Marie Martin|Mixte|Débutant",
  "2026-10-26-10-terrain1": "ENTRAINEMENT|Marie Martin|Mixte|Débutant",
  "2026-10-26-11-terrain1": "ENTRAINEMENT|Marie Martin|Mixte|Débutant",
  "2026-11-2-10-terrain1": "ENTRAINEMENT|Marie Martin|Mixte|Débutant",
  "2026-11-2-11-terrain1": "ENTRAINEMENT|Marie Martin|Mixte|Débutant",
  "2026-11-9-10-terrain1": "ENTRAINEMENT|Marie Martin|Mixte|Débutant",
  "2026-11-9-11-terrain1": "ENTRAINEMENT|Marie Martin|Mixte|Débutant",
  "2026-11-16-10-terrain1": "ENTRAINEMENT|Marie Martin|Mixte|Débutant",
  "2026-11-16-11-terrain1": "ENTRAINEMENT|Marie Martin|Mixte|Débutant",
  "2026-11-23-10-terrain1": "ENTRAINEMENT|Marie Martin|Mixte|Débutant",
  "2026-11-23-11-terrain1": "ENTRAINEMENT|Marie Martin|Mixte|Débutant",
  "2026-11-30-10-terrain1": "ENTRAINEMENT|Marie Martin|Mixte|Débutant",
  "2026-11-30-11-terrain1": "ENTRAINEMENT|Marie Martin|Mixte|Débutant",
  "2026-12-7-10-terrain1": "ENTRAINEMENT|Marie Martin|Mixte|Débutant",
  "2026-12-7-11-terrain1": "ENTRAINEMENT|Marie Martin|Mixte|Débutant",
  "2026-12-14-10-terrain1": "ENTRAINEMENT|Marie Martin|Mixte|Débutant",
  "2026-12-14-11-terrain1": "ENTRAINEMENT|Marie Martin|Mixte|Débutant",
  "2026-12-21-10-terrain1": "ENTRAINEMENT|Marie Martin|Mixte|Débutant",
  "2026-12-21-11-terrain1": "ENTRAINEMENT|Marie Martin|Mixte|Débutant",
  "2026-12-28-10-terrain1": "ENTRAINEMENT|Marie Martin|Mixte|Débutant",
  "2026-12-28-11-terrain1": "ENTRAINEMENT|Marie Martin|Mixte|Débutant",
  "2026-1-5-10-terrain2": "ENTRAINEMENT|Marie Martin|Mixte|Intermédiaire",
  "2026-1-5-11-terrain2": "ENTRAINEMENT|Marie Martin|Mixte|Intermédiaire",
  "2026-1-12-10-terrain2": "ENTRAINEMENT|Marie Martin|Mixte|Intermédiaire",
  "2026-1-12-11-terrain2": "ENTRAINEMENT|Marie Martin|Mixte|Intermédiaire",
  "2026-1-19-10-terrain2": "ENTRAINEMENT|Marie Martin|Mixte|Intermédiaire",
  "2026-1-19-11-terrain2": "ENTRAINEMENT|Marie Martin|Mixte|Intermédiaire",
  "2026-1-26-10-terrain2": "ENTRAINEMENT|Marie Martin|Mixte|Intermédiaire",
  "2026-1-26-11-terrain2": "ENTRAINEMENT|Marie Martin|Mixte|Intermédiaire",
  "2026-2-2-10-terrain2": "ENTRAINEMENT|Marie Martin|Mixte|Intermédiaire",
  "2026-2-2-11-terrain2": "ENTRAINEMENT|Marie Martin|Mixte|Intermédiaire",
  "2026-2-9-10-terrain2": "ENTRAINEMENT|Marie Martin|Mixte|Intermédiaire",
  "2026-2-9-11-terrain2": "ENTRAINEMENT|Marie Martin|Mixte|Intermédiaire",
  "2026-2-16-10-terrain2": "ENTRAINEMENT|Marie Martin|Mixte|Intermédiaire",
  "2026-2-16-11-terrain2": "ENTRAINEMENT|Marie Martin|Mixte|Intermédiaire",
  "2026-2-23-10-terrain2": "ENTRAINEMENT|Marie Martin|Mixte|Intermédiaire",
  "2026-2-23-11-terrain2": "ENTRAINEMENT|Marie Martin|Mixte|Intermédiaire",
  "2026-3-2-10-terrain2": "ENTRAINEMENT|Marie Martin|Mixte|Intermédiaire",
  "2026-3-2-11-terrain2": "ENTRAINEMENT|Marie Martin|Mixte|Intermédiaire",
  "2026-3-9-10-terrain2": "ENTRAINEMENT|Marie Martin|Mixte|Intermédiaire",
  "2026-3-9-11-terrain2": "ENTRAINEMENT|Marie Martin|Mixte|Intermédiaire",
  "2026-3-16-10-terrain2": "ENTRAINEMENT|Marie Martin|Mixte|Intermédiaire",
  "2026-3-16-11-terrain2": "ENTRAINEMENT|Marie Martin|Mixte|Intermédiaire",
  "2026-3-23-10-terrain2": "ENTRAINEMENT|Marie Martin|Mixte|Intermédiaire",
  "2026-3-23-11-terrain2": "ENTRAINEMENT|Marie Martin|Mixte|Intermédiaire",
  "2026-3-30-10-terrain2": "ENTRAINEMENT|Marie Martin|Mixte|Intermédiaire",
  "2026-3-30-11-terrain2": "ENTRAINEMENT|Marie Martin|Mixte|Intermédiaire",
  "2026-4-6-10-terrain2": "ENTRAINEMENT|Marie Martin|Mixte|Intermédiaire",
  "2026-4-6-11-terrain2": "ENTRAINEMENT|Marie Martin|Mixte|Intermédiaire",
  "2026-4-13-10-terrain2": "ENTRAINEMENT|Marie Martin|Mixte|Intermédiaire",
  "2026-4-13-11-terrain2": "ENTRAINEMENT|Marie Martin|Mixte|Intermédiaire",
  "2026-4-20-10-terrain2": "ENTRAINEMENT|Marie Martin|Mixte|Intermédiaire",
  "2026-4-20-11-terrain2": "ENTRAINEMENT|Marie Martin|Mixte|Intermédiaire",
  "2026-4-27-10-terrain2": "ENTRAINEMENT|Marie Martin|Mixte|Intermédiaire",
  "2026-4-27-11-terrain2": "ENTRAINEMENT|Marie Martin|Mixte|Intermédiaire",
  "2026-5-4-10-terrain2": "ENTRAINEMENT|Marie Martin|Mixte|Intermédiaire",
  "2026-5-4-11-terrain2": "ENTRAINEMENT|Marie Martin|Mixte|Intermédiaire",
  "2026-5-11-10-terrain2": "ENTRAINEMENT|Marie Martin|Mixte|Intermédiaire",
  "2026-5-11-11-terrain2": "ENTRAINEMENT|Marie Martin|Mixte|Intermédiaire",
  "2026-5-18-10-terrain2": "ENTRAINEMENT|Marie Martin|Mixte|Intermédiaire",
  "2026-5-18-11-terrain2": "ENTRAINEMENT|Marie Martin|Mixte|Intermédiaire",
  "2026-5-25-10-terrain2": "ENTRAINEMENT|Marie Martin|Mixte|Intermédiaire",
  "2026-5-25-11-terrain2": "ENTRAINEMENT|Marie Martin|Mixte|Intermédiaire",
  "2026-6-1-10-terrain2": "ENTRAINEMENT|Marie Martin|Mixte|Intermédiaire",
  "2026-6-1-11-terrain2": "ENTRAINEMENT|Marie Martin|Mixte|Intermédiaire",
  "2026-6-8-10-terrain2": "ENTRAINEMENT|Marie Martin|Mixte|Intermédiaire",
  "2026-6-8-11-terrain2": "ENTRAINEMENT|Marie Martin|Mixte|Intermédiaire",
  "2026-6-15-10-terrain2": "ENTRAINEMENT|Marie Martin|Mixte|Intermédiaire",
  "2026-6-15-11-terrain2": "ENTRAINEMENT|Marie Martin|Mixte|Intermédiaire",
  "2026-6-22-10-terrain2": "ENTRAINEMENT|Marie Martin|Mixte|Intermédiaire",
  "2026-6-22-11-terrain2": "ENTRAINEMENT|Marie Martin|Mixte|Intermédiaire",
  "2026-6-29-10-terrain2": "ENTRAINEMENT|Marie Martin|Mixte|Intermédiaire",
  "2026-6-29-11-terrain2": "ENTRAINEMENT|Marie Martin|Mixte|Intermédiaire",
  "2026-7-6-10-terrain2": "ENTRAINEMENT|Marie Martin|Mixte|Intermédiaire",
  "2026-7-6-11-terrain2": "ENTRAINEMENT|Marie Martin|Mixte|Intermédiaire",
  "2026-7-13-10-terrain2": "ENTRAINEMENT|Marie Martin|Mixte|Intermédiaire",
  "2026-7-13-11-terrain2": "ENTRAINEMENT|Marie Martin|Mixte|Intermédiaire",
  "2026-7-20-10-terrain2": "ENTRAINEMENT|Marie Martin|Mixte|Intermédiaire",
  "2026-7-20-11-terrain2": "ENTRAINEMENT|Marie Martin|Mixte|Intermédiaire",
  "2026-7-27-10-terrain2": "ENTRAINEMENT|Marie Martin|Mixte|Intermédiaire",
  "2026-7-27-11-terrain2": "ENTRAINEMENT|Marie Martin|Mixte|Intermédiaire",
  "2026-8-3-10-terrain2": "ENTRAINEMENT|Marie Martin|Mixte|Intermédiaire",
  "2026-8-3-11-terrain2": "ENTRAINEMENT|Marie Martin|Mixte|Intermédiaire",
  "2026-8-10-10-terrain2": "ENTRAINEMENT|Marie Martin|Mixte|Intermédiaire",
  "2026-8-10-11-terrain2": "ENTRAINEMENT|Marie Martin|Mixte|Intermédiaire",
  "2026-8-17-10-terrain2": "ENTRAINEMENT|Marie Martin|Mixte|Intermédiaire",
  "2026-8-17-11-terrain2": "ENTRAINEMENT|Marie Martin|Mixte|Intermédiaire",
  "2026-8-24-10-terrain2": "ENTRAINEMENT|Marie Martin|Mixte|Intermédiaire",
  "2026-8-24-11-terrain2": "ENTRAINEMENT|Marie Martin|Mixte|Intermédiaire",
  "2026-8-31-10-terrain2": "ENTRAINEMENT|Marie Martin|Mixte|Intermédiaire",
  "2026-8-31-11-terrain2": "ENTRAINEMENT|Marie Martin|Mixte|Intermédiaire",
  "2026-9-7-10-terrain2": "ENTRAINEMENT|Marie Martin|Mixte|Intermédiaire",
  "2026-9-7-11-terrain2": "ENTRAINEMENT|Marie Martin|Mixte|Intermédiaire",
  "2026-9-14-10-terrain2": "ENTRAINEMENT|Marie Martin|Mixte|Intermédiaire",
  "2026-9-14-11-terrain2": "ENTRAINEMENT|Marie Martin|Mixte|Intermédiaire",
  "2026-9-21-10-terrain2": "ENTRAINEMENT|Marie Martin|Mixte|Intermédiaire",
  "2026-9-21-11-terrain2": "ENTRAINEMENT|Marie Martin|Mixte|Intermédiaire",
  "2026-9-28-10-terrain2": "ENTRAINEMENT|Marie Martin|Mixte|Intermédiaire",
  "2026-9-28-11-terrain2": "ENTRAINEMENT|Marie Martin|Mixte|Intermédiaire",
  "2026-10-5-10-terrain2": "ENTRAINEMENT|Marie Martin|Mixte|Intermédiaire",
  "2026-10-5-11-terrain2": "ENTRAINEMENT|Marie Martin|Mixte|Intermédiaire",
  "2026-10-12-10-terrain2": "ENTRAINEMENT|Marie Martin|Mixte|Intermédiaire",
  "2026-10-12-11-terrain2": "ENTRAINEMENT|Marie Martin|Mixte|Intermédiaire",
  "2026-10-19-10-terrain2": "ENTRAINEMENT|Marie Martin|Mixte|Intermédiaire",
  "2026-10-19-11-terrain2": "ENTRAINEMENT|Marie Martin|Mixte|Intermédiaire",
  "2026-10-26-10-terrain2": "ENTRAINEMENT|Marie Martin|Mixte|Intermédiaire",
  "2026-10-26-11-terrain2": "ENTRAINEMENT|Marie Martin|Mixte|Intermédiaire",
  "2026-11-2-10-terrain2": "ENTRAINEMENT|Marie Martin|Mixte|Intermédiaire",
  "2026-11-2-11-terrain2": "ENTRAINEMENT|Marie Martin|Mixte|Intermédiaire",
  "2026-11-9-10-terrain2": "ENTRAINEMENT|Marie Martin|Mixte|Intermédiaire",
  "2026-11-9-11-terrain2": "ENTRAINEMENT|Marie Martin|Mixte|Intermédiaire",
  "2026-11-16-10-terrain2": "ENTRAINEMENT|Marie Martin|Mixte|Intermédiaire",
  "2026-11-16-11-terrain2": "ENTRAINEMENT|Marie Martin|Mixte|Intermédiaire",
  "2026-11-23-10-terrain2": "ENTRAINEMENT|Marie Martin|Mixte|Intermédiaire",
  "2026-11-23-11-terrain2": "ENTRAINEMENT|Marie Martin|Mixte|Intermédiaire",
  "2026-11-30-10-terrain2": "ENTRAINEMENT|Marie Martin|Mixte|Intermédiaire",
  "2026-11-30-11-terrain2": "ENTRAINEMENT|Marie Martin|Mixte|Intermédiaire",
  "2026-12-7-10-terrain2": "ENTRAINEMENT|Marie Martin|Mixte|Intermédiaire",
  "2026-12-7-11-terrain2": "ENTRAINEMENT|Marie Martin|Mixte|Intermédiaire",
  "2026-12-14-10-terrain2": "ENTRAINEMENT|Marie Martin|Mixte|Intermédiaire",
  "2026-12-14-11-terrain2": "ENTRAINEMENT|Marie Martin|Mixte|Intermédiaire",
  "2026-12-21-10-terrain2": "ENTRAINEMENT|Marie Martin|Mixte|Intermédiaire",
  "2026-12-21-11-terrain2": "ENTRAINEMENT|Marie Martin|Mixte|Intermédiaire",
  "2026-12-28-10-terrain2": "ENTRAINEMENT|Marie Martin|Mixte|Intermédiaire",
  "2026-12-28-11-terrain2": "ENTRAINEMENT|Marie Martin|Mixte|Intermédiaire",
  "2026-1-26-0-terrain1": "",
  "2026-1-26-0-terrain2": "",
  "2026-1-26-1-terrain1": "",
  "2026-1-26-1-terrain2": "",
  "2026-1-26-2-terrain1": "",
  "2026-1-26-2-terrain2": "",
  "2026-1-26-3-terrain1": "",
  "2026-1-26-3-terrain2": "",
  "2026-1-26-4-terrain1": "",
  "2026-1-26-4-terrain2": "",
  "2026-1-26-5-terrain1": "",
  "2026-1-26-5-terrain2": "",
  "2026-1-26-6-terrain1": "",
  "2026-1-26-6-terrain2": "",
  "2026-1-26-7-terrain1": "",
  "2026-1-26-7-terrain2": "",
  "2026-1-26-8-terrain1": "",
  "2026-1-26-8-terrain2": "",
  "2026-1-26-9-terrain1": "",
  "2026-1-26-9-terrain2": "",
  "2026-1-26-12-terrain1": "",
  "2026-1-26-12-terrain2": "",
  "2026-1-26-13-terrain1": "",
  "2026-1-26-13-terrain2": "",
  "2026-1-27-0-terrain1": "",
  "2026-1-27-0-terrain2": "",
  "2026-1-27-1-terrain1": "",
  "2026-1-27-1-terrain2": "",
  "2026-1-27-2-terrain1": "",
  "2026-1-27-2-terrain2": "",
  "2026-1-27-3-terrain1": "",
  "2026-1-27-3-terrain2": "",
  "2026-1-27-4-terrain1": "",
  "2026-1-27-4-terrain2": "",
  "2026-1-27-5-terrain1": "",
  "2026-1-27-5-terrain2": "",
  "2026-1-27-6-terrain1": "",
  "2026-1-27-6-terrain2": "",
  "2026-1-27-7-terrain1": "",
  "2026-1-27-7-terrain2": "",
  "2026-1-27-8-terrain1": "",
  "2026-1-27-8-terrain2": "",
  "2026-1-27-9-terrain1": "",
  "2026-1-27-9-terrain2": "",
  "2026-1-27-12-terrain1": "",
  "2026-1-27-12-terrain2": "",
  "2026-1-27-13-terrain1": "",
  "2026-1-27-13-terrain2": "",
  "2026-2-28-1-terrain1": "TOURNOI|S3|Masculin",
  "2026-2-28-1-terrain2": "TOURNOI|S3|Masculin",
  "2026-2-28-2-terrain1": "TOURNOI|S3|Masculin",
  "2026-2-28-2-terrain2": "TOURNOI|S3|Masculin",
  "2026-2-28-3-terrain1": "TOURNOI|S3|Masculin",
  "2026-2-28-3-terrain2": "TOURNOI|S3|Masculin",
  "2026-2-28-4-terrain1": "TOURNOI|S3|Masculin",
  "2026-2-28-4-terrain2": "TOURNOI|S3|Masculin",
  "2026-2-28-5-terrain1": "TOURNOI|S3|Masculin",
  "2026-2-28-5-terrain2": "TOURNOI|S3|Masculin",
  "2026-2-28-6-terrain1": "TOURNOI|S3|Masculin",
  "2026-2-28-6-terrain2": "TOURNOI|S3|Masculin",
  "2026-2-28-7-terrain1": "TOURNOI|S3|Masculin",
  "2026-2-28-7-terrain2": "TOURNOI|S3|Masculin",
  "2026-2-28-8-terrain1": "TOURNOI|S3|Masculin",
  "2026-2-28-8-terrain2": "TOURNOI|S3|Masculin",
  "2026-2-28-9-terrain1": "TOURNOI|S3|Masculin",
  "2026-2-28-9-terrain2": "TOURNOI|S3|Masculin",
  "2026-2-27-0-terrain1": "",
  "2026-2-27-0-terrain2": "",
  "2026-2-27-1-terrain1": "",
  "2026-2-27-1-terrain2": "",
  "2026-2-27-2-terrain1": "Thomas Lefevre",
  "2026-2-27-2-terrain2": "Thomas Lefevre",
  "2026-2-27-3-terrain1": "",
  "2026-2-27-3-terrain2": "",
  "2026-2-27-4-terrain1": "",
  "2026-2-27-4-terrain2": "",
  "2026-2-27-5-terrain1": "Thomas Lefevre",
  "2026-2-27-5-terrain2": "Thomas Lefevre",
  "2026-2-27-6-terrain1": "",
  "2026-2-27-6-terrain2": "",
  "2026-2-27-7-terrain1": "",
  "2026-2-27-7-terrain2": "",
  "2026-2-27-8-terrain1": "",
  "2026-2-27-8-terrain2": "",
  "2026-2-27-9-terrain1": "",
  "2026-2-27-9-terrain2": "",
  "2026-2-27-10-terrain1": "",
  "2026-2-27-10-terrain2": "",
  "2026-2-27-11-terrain1": "",
  "2026-2-27-11-terrain2": "",
  "2026-2-27-12-terrain1": "",
  "2026-2-27-12-terrain2": "",
  "2026-2-27-13-terrain1": "",
  "2026-2-27-13-terrain2": "",
  "2026-2-27-2-max_places": 8,
  "2026-2-27-2-joueurs": [
    "Claire Moreau",
    "Emma Laurent",
    "Julien Roux",
    "Olivier Simon"
  ],
  "2026-2-27-5-max_places": 10,
  "2026-2-27-5-joueurs": []
}